dbus_idle/__init__.py
dbus_idle/__main__.py
dbus_idle-2025.5.1.dist-info/LICENSE
dbus_idle-2025.5.1.dist-info/METADATA
dbus_idle-2025.5.1.dist-info/WHEEL
dbus_idle-2025.5.1.dist-info/entry_points.txt
dbus_idle-2025.5.1.dist-info/top_level.txt
dbus_idle-2025.5.1.dist-info/RECORD
