Metadata-Version: 2.1
Name: dbus-idle
Version: 2025.5.1
Summary: System idle time using DBus
Home-page: https://github.com/bkbilly/dbus_idle
Author-email: Alexander Frenzel <alex@relatedworks.com>, bkbilly <bkbilly@hotmail.com>
Project-URL: Source Code, https://github.com/bkbilly/dbus_idle
Keywords: dbus_idle,dbus-idle
Classifier: Programming Language :: Python :: 3
Classifier: License :: OSI Approved :: BSD License
Classifier: Operating System :: OS Independent
Requires-Python: >=3.7.0
License-File: LICENSE
Requires-Dist: jeepney (>=0.9.0) ; platform_system != "Windows"
Requires-Dist: pywin32 (>=221) ; platform_system == "Windows"
